openclimate/ActorOverview.py
openclimate/Base.py
openclimate/Client.py
openclimate/Emissions.py
openclimate/GDP.py
openclimate/Population.py
openclimate/Search.py
openclimate/Targets.py
openclimate/Tools.py
openclimate/__init__.py
openclimate/utils.py
openclimate-0.1.5.dist-info/LICENSE
openclimate-0.1.5.dist-info/METADATA
openclimate-0.1.5.dist-info/WHEEL
openclimate-0.1.5.dist-info/top_level.txt
openclimate-0.1.5.dist-info/RECORD
